pyg2plot/__init__.py
pyg2plot/engine.py
pyg2plot/meta.py
pyg2plot/plot.py
pyg2plot/helper/__init__.py
pyg2plot/helper/code.py
pyg2plot/helper/file.py
pyg2plot/helper/html.py
pyg2plot/templates/jupyter-lab.html
pyg2plot/templates/notebook.html
pyg2plot/templates/plot.html
pyg2plot-0.1.8.dist-info/LICENSE
pyg2plot-0.1.8.dist-info/METADATA
pyg2plot-0.1.8.dist-info/WHEEL
pyg2plot-0.1.8.dist-info/top_level.txt
pyg2plot-0.1.8.dist-info/RECORD
