Metadata-Version: 2.1
Name: pyg2plot
Version: 0.1.8
Summary: Python3 binding for `@AntV/G2Plot` Plotting Library, make charting easier.
Home-page: https://github.com/hustcc/pyg2plot
Author: hustcc
Author-email: i@hust.cc
License: MIT
Keywords: AntV,G2Plot,charts,PyG2Plot,visualization
Platform: UNKNOWN
Classifier: Environment :: Console
Classifier: Intended Audience :: Developers
Classifier: License :: OSI Approved :: MIT License
Classifier: Operating System :: OS Independent
Classifier: Programming Language :: Python
Classifier: Programming Language :: Python :: 3
Classifier: Programming Language :: Python :: 3.6
Classifier: Programming Language :: Python :: 3.7
Classifier: Programming Language :: Python :: 3.8
Classifier: Programming Language :: Python :: 3.9
Classifier: Topic :: Software Development :: Libraries
Requires-Dist: jinja2 (~=2.11.2)
Requires-Dist: simplejson
